translate/__init__.py
translate/__main__.py
translate/translate.py
translateit-0.0.31.dist-info/DESCRIPTION.rst
translateit-0.0.31.dist-info/METADATA
translateit-0.0.31.dist-info/RECORD
translateit-0.0.31.dist-info/WHEEL
translateit-0.0.31.dist-info/entry_points.txt
translateit-0.0.31.dist-info/metadata.json
translateit-0.0.31.dist-info/top_level.txt
