Metadata-Version: 2.0
Name: translateit
Version: 0.0.31
Summary: This is a simple console translator
Home-page: UNKNOWN
Author: KIDJourney
Author-email: kingdeadfish@qq.com
License: MIT
Keywords: hello world translate requests
Platform: UNKNOWN
Classifier: Programming Language :: Python :: 3.4
Requires-Dist: requests
